nonebot_anywhere_llm/__init__.py
nonebot_anywhere_llm/config.py
nonebot_anywhere_llm/history_manager.py
nonebot_anywhere_llm/llm_service.py
nonebot_anywhere_llm/models/__init__.py
nonebot_anywhere_llm/models/llm_params.py
nonebot_anywhere_llm/provider/__init__.py
nonebot_anywhere_llm/provider/interface.py
nonebot_anywhere_llm/provider/openai.py
nonebot_anywhere_llm/test/__init__.py
nonebot_anywhere_llm/utils/__init__.py
nonebot_anywhere_llm/utils/llm_time.py
nonebot_anywhere_llm/utils/prompt.py
nonebot_anywhere_llm-0.5.0.dist-info/LICENSE
nonebot_anywhere_llm-0.5.0.dist-info/METADATA
nonebot_anywhere_llm-0.5.0.dist-info/WHEEL
nonebot_anywhere_llm-0.5.0.dist-info/RECORD
