Metadata-Version: 2.3
Name: nonebot_anywhere_llm
Version: 0.5.0
Summary: Nonebot2 plugin for using llm
License: MIT
Author: Zeta-qixi
Author-email: 1019289695@qq.com
Requires-Python: >=3.9,<4.0
Classifier: License :: OSI Approved :: MIT License
Classifier: Programming Language :: Python :: 3
Classifier: Programming Language :: Python :: 3.9
Classifier: Programming Language :: Python :: 3.10
Classifier: Programming Language :: Python :: 3.11
Classifier: Programming Language :: Python :: 3.12
Classifier: Programming Language :: Python :: 3.13
Requires-Dist: aiosqlite (>=0.21.0,<0.22.0)
Requires-Dist: nonebot-adapter-onebot (>=2.4.3,<3.0.0)
Requires-Dist: nonebot2 (>=2.4.1,<3.0.0)
Requires-Dist: openai (>=1.43.0,<2.0.0)
Project-URL: Homepage, https://github.com/Zeta-qixi/nonebot-plugin-anywhere-llm
